pybib2web/__init__.py
pybib2web/bibexport.py
pybib2web/bibparser.py
pybib2web/categories.py
pybib2web/config.py
pybib2web/htmlexport.py
pybib2web/util.py
pybib2web/version.py
pybib2web-0.6.dist-info/Apache-2.0.txt
pybib2web-0.6.dist-info/METADATA
pybib2web-0.6.dist-info/WHEEL
pybib2web-0.6.dist-info/entry_points.txt
pybib2web-0.6.dist-info/top_level.txt
pybib2web-0.6.dist-info/zip-safe
pybib2web-0.6.dist-info/RECORD
