Metadata-Version: 2.1
Name: pybib2web
Version: 0.6
Summary: A translator of BibTeX to HTML.
Home-page: https://gitlab.com/sosy-lab/software/pybib2web
Author: Dirk Beyer
Author-email: dirk.beyer@sosy-lab.org
License: Apache-2.0
Project-URL: Changelog, https://gitlab.com/sosy-lab/software/pybib2web/-/blob/main/CHANGELOG.md
Project-URL: Issue Tracker, https://gitlab.com/sosy-lab/software/pybib2web/-/issues
Keywords: bibliography,BibTeX
Classifier: Development Status :: 4 - Beta
Classifier: Environment :: Console
Classifier: Intended Audience :: Science/Research
Classifier: License :: OSI Approved :: Apache Software License
Classifier: Operating System :: POSIX :: Linux
Classifier: Programming Language :: Python :: 3 :: Only
Classifier: Topic :: Text Processing :: Markup :: LaTeX
License-File: LICENSES/Apache-2.0.txt
Requires-Dist: bibtexparser >=1.2
Requires-Dist: PyYAML >=5.3
